LICENSE
MANIFEST.in
README.md
setup.py
AON/maker.py
AON/man.py
AON.egg-info/PKG-INFO
AON.egg-info/SOURCES.txt
AON.egg-info/dependency_links.txt
AON.egg-info/entry_points.txt
AON.egg-info/top_level.txt