Metadata-Version: 2.1
Name: AON
Version: 1.0.7
Summary: Advanced object notation based on python.
Home-page: UNKNOWN
Author: Koppula Praveen Kumar
Author-email: koppulapraveen920@gmail.com
License: MIT
Platform: UNKNOWN
Classifier: License :: OSI Approved :: MIT License
Classifier: Programming Language :: Python :: 3
Classifier: Programming Language :: Python :: 3.7
License-File: LICENSE
